fibonacci_index/__init__.py
fibonacci_index/fibonacci_index.py
fibonacci_index-0.0.2.dist-info/LICENCE
fibonacci_index-0.0.2.dist-info/METADATA
fibonacci_index-0.0.2.dist-info/WHEEL
fibonacci_index-0.0.2.dist-info/top_level.txt
fibonacci_index-0.0.2.dist-info/RECORD
