Metadata-Version: 2.1
Name: fibonacci-index
Version: 0.0.2
Summary: A small example package
Home-page: https://github.com/ifcassianasl/fibonacci-index
Author: Cassiana Silveira
Author-email: cassianasilveira64@gmail.com
License: UNKNOWN
Project-URL: Bug Tracker, https://github.com/ifcassianasl/fibonacci-index/issues
Platform: UNKNOWN
Classifier: Programming Language :: Python :: 3
Classifier: License :: OSI Approved :: MIT License
Classifier: Operating System :: OS Independent
Requires-Python: >=3.6
